Workbook

Sheet COGS
A1: Désignation | B1: Unité | C1: Quantité | D1: Multiplicateur | E1: Unitaire (Ar) | F1: Montant (Ar)
A2: CHARGES DU PERSONNELS
A3: Salaire Chef d'équipe | B3: Mois | C3: 20 | D3: 3 | E3: 230000 | F3: =C3*D3*E3 -> 13800000
A4: Salaire Personnels | B4: Mois | C4: 14 | D4: 12 | E4: 200000 | F4: =C4*D4*E4 -> 33600000
A5: Salaire Chef d'équipe CNAPS | B5: Mois | C5: 9 | D5: 2 | E5: 287000 | F5: =C5*D5*E5 -> 5166000
A6: Salaire Personnels CNAPS | B6: Mois | C6: 9 | D6: 11 | E6: 267000 | F6: =C6*D6*E6 -> 26433000
A7: Cantines | B7: Jour | C7: 22 | D7: 10 | E7: 30000 | F7: =C7*D7*E7 -> 6600000
A8: Transport personnels | B8: Jour | C8: 22 | D8: 10 | E8: 35000 | F8: =C8*D8*E8 -> 7700000
A9: Achat EPI | B9: Pack | C9: 2 | D9: 11 | E9: 50000 | F9: =C9*D9*E9 -> 1100000
A10: CHARGES IMMOBILIERES ET MOBILIERES
A11: Hangar BSF | B11: Unité | C11: 1 | D11: 1 | E11: 60000000 | F11: =C11*D11*E11 -> 60000000
A12: Amortissement Machine 1 | B12: Mois | C12: 24 | D12: 1 | E12: 226190 | F12: =C12*D12*E12 -> 5428560
A13: Amortissement Machine 2 | B13: Mois | C13: 24 | D13: 1 | E13: 134875 | F13: =C13*D13*E13 -> 3237000
A14: Amortissement Machine 3 | B14: Mois | C14: 24 | D14: 1 | E14: 138416 | F14: =C14*D14*E14 -> 3321984
A15: Amortissement Machine 4 | B15: Mois | C15: 24 | D15: 1 | E15: 233333 | F15: =C15*D15*E15 -> 5599992
A16: Amortissement machine 5 | B16: Mois | C16: 24 | D16: 1 | E16: 233333 | F16: =C16*D16*E16 -> 5599992
A17: Amortissement Tracteur | B17: Mois | C17: 24 | D17: 1 | E17: =Tableau132[[#This Row],[Montant (Ar)]]/Tableau132[[#This Row],[Quantité]] -> 250000 | F17: 6000000
A18: Amortissement Kubota | B18: Mois | C18: 24 | D18: 1 | E18: 120000 | F18: =C18*D18*E18 -> 2880000
A19: ACHATS MATIERES PREMIERES
A20: Achat Tomates en boite périmé | B20: Tonnes | C20: 45.066 | D20: 1 | E20: 42850 | F20: =C20*D20*E20 -> 1931078.1
A21: Achat Fientes de poule | B21: Tonnes | C21: ='Production BSF'!A19/4/1000 -> 70.515 | D21: 1 | E21: 50000 | F21: =C21*D21*E21 -> 3525750
A22: Valeur MP Ntsoa utilisées | B22: Tonnes | C22: 17 | D22: 1 | E22: 800000 | F22: =C22*D22*E22 -> 13600000
A23: Achat Coquillage | B23: Tonnes | C23: ='Production BSF'!A19/1000*0.05 -> 14.103 | D23: 1 | E23: 80000 | F23: =C23*D23*E23 -> 1128240
A24: Collecte déchets de Litchi | B24: Tonnes | C24: ='Production BSF'!A19*2/1000 -> 564.12 | D24: 1 | E24: 0 | F24: =C24*D24*E24 -> 0
A25: Achat emballage | B25: Unité | C25: ='Production BSF'!A19/30 -> 9402 | D25: 1 | E25: 1600 | F25: =C25*D25*E25 -> 15043200
A26: Achat 5DOL Black soldier Fly | B26: Kg | C26: 10 | D26: 2 | E26: 150000 | F26: =C26*D26*E26 -> 3000000
A27: ENERGIES
A28: Carburant Camion Collecte | B28: L | C28: =(C24+C21)*0.5 -> 317.3175 | D28: 1 | E28: 4900 | F28: =C28*D28*E28 -> 1554855.8
A29: Carburant Kubota Collecte | B29: L | C29: =(C24+C22)*0.25 -> 145.28 | D29: 1 | E29: 4900 | F29: =C29*D29*E29 -> 711872
A30: Facture Electricité | B30: KWh | C30: 20 | D30: 29 | E30: 51249 | F30: =C30*D30*E30 -> 29724420
A31: DEPENSES DIVERSES
A32: Frais de livraison PUPRA | B32: Kg | C32: ='Production BSF'!A19-('Production BSF'!C10+'Production BSF'!C11+'Production BSF'!C12+'Production BSF'!C13+'Production BSF'!C14+'Production BSF'!C15) -> 112680 | D32: 1 | E32: 40 | F32: =C32*D32*E32 -> 4507200
A33: Dépenses équipes | B33: Kg | C33: ='Production BSF'!A19-('Production BSF'!C10+'Production BSF'!C11+'Production BSF'!C12+'Production BSF'!C13+'Production BSF'!C14+'Production BSF'!C15) -> 112680 | D33: 1 | E33: 20 | F33: =C33*D33*E33 -> 2253600
A35: COMMUNICATION
A36: Flotte téléphonique | B36: Util | C36: 3 | D36: 24 | E36: 50000 | F36: =Tableau132[[#This Row],[Quantité]]*Tableau132[[#This Row],[Multiplicateur]]*Tableau132[[#This Row],[Unitaire (Ar)]] -> 3600000
A37: Connexion | B37: Abonn | C37: 1 | D37: 24 | E37: 100000 | F37: =Tableau132[[#This Row],[Quantité]]*Tableau132[[#This Row],[Multiplicateur]]*Tableau132[[#This Row],[Unitaire (Ar)]] -> 2400000
E38: TGR | F38: =SUBTOTAL(109,F2:F37) -> 2.6944674e+08
E39: REVIENT PAR KG | F39: =F38/'Production BSF'!A19 -> 955.28166

Sheet Production BSF
A1: Quantification | B1: Unité | C1: Quantité (Kg) | D1: Clients | E1: Date | F1: Column1
A2: 67 | B2: sacs (30kg) | C2: =A2*30 -> 2010 | D2: Phael Flor | E2: Novembre 2023
A3: 517 | B3: Bénéficiaire (90kg) | C3: =A3*90 -> 46530 | D3: Purpa 2024 | E3: Mars 2024
A4: 19000 | B4: Tonne | C4: 19000 | D4: Ambohijanaka | E4: Septembre 2024
B5: Tonne | C5: 4000 | D5: Ambatondrazaka
B6: Tonne | C6: 2000 | D6: Pst Reynaud
A7: 145 | B7: Bénéficiaire (90kg) | C7: =A7*90 -> 13050 | D7: Purpa Brickaville | E7: Mai 2024
A8: 100 | B8: Bénéficiaire (215kg) | C8: =A8*215 -> 21500 | D8: Titre vert | E8: Octobre 2024
A9: 51 | B9: Bénéficiaire (90kg) | C9: 4590 | D9: Purpa 2025 | E9: Décembre 2024
A10: 23000 | B10: Tonne | C10: 23000 | D10: Stock non traité | E10: Novembre 2024
A11: 385 | B11: sacs (30kg) | C11: 11500 | D11: Stock dispo | E11: Décembre
A12: 1486 | B12: sacs (30kg) | C12: =A12*30 -> 44580
A13: 964 | C13: =A13*30 -> 28920
A14: 703 | C14: =A14*30 -> 21090
A15: 1343 | C15: =A15*30 -> 40290
A18: TOTAL PROD | B18: MOIS D'EXERCICE | C18: PROD/MENSUEL | D18: N JOUR TRAVAIL | E18: PROD JOURNALIER | F18: TOTAL JOUR TRAVAIL
A19: =SUM(C2:C15) -> 282060 | B19: 24 | C19: =A19/B19 -> 11752.5 | D19: 20 | E19: =C19/D19 -> 587.625 | F19: =D19*B19 -> 480

Sheet Produits NPKSemences
A1: Produits | B1: Quantité | C1: Unitaire | D1: Montant | E1: Date
A2: NPK | B2: 15600 | C2: 4540 | D2: =B2*C2 -> 70824000 | E2: Mars 2024
A3: Riz | B3: 6000 | C3: 3800 | D3: =B3*C3 -> 22800000 | E3: Mars 2024
A4: NPK | B4: 5400 | C4: 3800 | D4: =B4*C4 -> 20520000 | E4: 45536
A5: NPK | B5: 650 | C5: 4300 | D5: =B5*C5 -> 2795000 | E5: Déc-2024
A6: Riz | B6: 500 | C6: 4000 | D6: =B6*C6 -> 2000000 | E6: 45597
A7: Mais | B7: 2800 | C7: 4500 | D7: =B7*C7 -> 12600000 | E7: Mai 2024
A8: Manioc | B8: 25000 | C8: 300 | D8: =B8*C8 -> 7500000 | E8: Mai 2024
D10: =SUM(D2:D9) -> 139039000

Sheet Vente 2023-2024
A1: VENTES ENCAISSEES | B1: Unité | C1: Quantité | D1: Unitaire | E1: Montant (Ar) | F1: VENTES NON ENCAISSEES
A2: Désignation | F2: Désignation | G2: Unité | H2: Quantité | I2: Unitaire | J2: Montant (Ar)
A3: Vente Phael Flor | B3: kg | C3: 2000 | D3: 1700 | E3: =C3*D3 -> 3400000 | F3: Vente TITRE VERT | G3: Kg | H3: =58*215 -> 12470 | I3: 2100 | J3: =H3*I3 -> 26187000
A4: Vente FDA-PURPA 2024 VAT | B4: kg | C4: =107*75 -> 8025 | D4: 1980 | E4: =C4*D4 -> 15889500 | F4: Vente NPK TITRE VERT | G4: Kg | H4: =58*110 -> 6380 | I4: 5800 | J4: =H4*I4 -> 37004000
A5: Vente FDA-PURPA 2024 TVE | B5: kg | C5: =406*75 -> 30450 | D5: 1890 | E5: =C5*D5 -> 57550500 | F5: Vente Maïs TITRE VERT | G5: Kg | H5: =58*14 -> 812 | I5: 5500 | J5: =H5*I5 -> 4466000
A6: Vente FDA-PURPA CR 2024 BRICK | B6: Kg | C6: =46*75 -> 3450 | D6: 1890 | E6: =C6*D6 -> 6520500 | F6: Vente Manioc TITRE VERT | G6: Kg | H6: =58*1250 -> 72500 | I6: 100 | J6: =H6*I6 -> 7250000
A7: Vente TITRE VERT | B7: Kg | C7: =42*215 -> 9030 | D7: 2100 | E7: =C7*D7 -> 18963000 | I7: TOTAL | J7: =SUM(J3:J6) -> 74907000
A8: Vente Ambohijanaka | B8: Kg | C8: 19000 | D8: 1000 | E8: =C8*D8 -> 19000000
A9: Vente Ambato | B9: kg | C9: 4000 | D9: 2000 | E9: =C9*D9 -> 8000000
A10: Vente Pst Reynaud | B10: Kg | C10: 2000 | D10: 2000 | E10: =C10*D10 -> 4000000
A11: Vente FDA-PURPA 2025 CR TVE | B11: Kg | C11: =51*75 -> 3825 | D11: 1890 | E11: =C11*D11 -> 7229250
A12: Vente Phael Flor | B12: Kg | C12: 1000 | D12: 1700 | E12: =C12*D12 -> 1700000
A13: Vente FDA-PURPA CR 2025 BRICK | B13: kg | C13: =98*75 -> 7350 | D13: 1890 | E13: =C13*D13 -> 13891500
A14: Vente FDA-PURPA 2025 TVE | B14: Kg | C14: =217*75 -> 16275 | D14: 1890 | E14: =C14*D14 -> 30759750
A15: Vente Foire carlton 2025 | B15: Kg | C15: 75 | D15: 2000 | E15: =C15*D15 -> 150000
A16: Vente extra TENDRY | B16: Kg | C16: 200 | D16: 2000 | E16: =C16*D16 -> 400000
A17: Vente boite de conserve tomate | B17: Kg | C17: 10000 | D17: 1000 | E17: =C17*D17 -> 10000000
A18: Revendeur Tana | B18: Kg | D18: 1800 | E18: =C18*D18 -> 0
C19: =SUM(C3:C14) -> 106405 | E19: =SUM(E3:E18) -> 197454000
A21: Vente NPK FDA-PURPA 2024 VAT | B21: Kg | C21: =107*15 -> 1605 | D21: 5400 | E21: =C21*D21 -> 8667000
A22: Vente NPK FDA-PURPA 2024 TVE | B22: Kg | C22: =406*15 -> 6090 | D22: 5220 | E22: =C22*D22 -> 31789800
A23: Vente NPK FDA-PURPA CR BRICK | B23: Kg | C23: =46*15 -> 690 | D23: 5220 | E23: =C23*D23 -> 3601800
A24: Vente NPK TITRE VERT | B24: Kg | C24: =42*110 -> 4620 | D24: 5800 | E24: =C24*D24 -> 26796000
A25: Vente NPK FDA-PURPA 2025 CR TVE | B25: Kg | C25: =51*15 -> 765 | D25: 5220 | E25: =C25*D25 -> 3993300
A26: Vente FDA-PURPA CR 2025 BRICK | B26: Kg | C26: =98*15 -> 1470 | D26: 5220 | E26: =C26*D26 -> 7673400
A27: Vente FDA-PURPA 2025 TVE | B27: Kg | C27: =217*15 -> 3255 | D27: 5220 | E27: =C27*D27 -> 16991100
C28: =SUM(C21:C25) -> 13770 | E28: =SUM(E21:E27) -> 99512400
A30: Vente Riz FDA-PURPA 2024 VAT | B30: Kg | C30: =107*9 -> 963 | D30: 4860 | E30: =C30*D30 -> 4680180
A31: Vente Riz FDA-PURPA 2024 TVE | B31: Kg | C31: =406*9 -> 3654 | D31: 4770 | E31: =C31*D31 -> 17429580
A32: Vente Riz FDA-PURPA CR BRICK | B32: Kg | C32: =46*9 -> 414 | D32: 4770 | E32: =C32*D32 -> 1974780
A33: Vente Maïs TITRE VERT | B33: Kg | C33: =42*14 -> 588 | D33: 5500 | E33: =C33*D33 -> 3234000
A34: Vente Manioc TITRE VERT | B34: Pièce | C34: =42*1250 -> 52500 | D34: 100 | E34: =C34*D34 -> 5250000
A35: Vente Riz FDA-PURPA 2025 CR TVE | B35: Kg | C35: =51*9 -> 459 | D35: 4770 | E35: =C35*D35 -> 2189430
A36: Vente Riz FDA-PURPA CR 2025 BRICK | B36: Kg | C36: =98*9 -> 882 | D36: 4770 | E36: =C36*D36 -> 4207140
A37: Vente Riz FDA-PURPA 2025 TVE | B37: Kg | C37: =217*9 -> 1953 | D37: 4770 | E37: =C37*D37 -> 9315810
E38: =SUM(E30:E37) -> 48280920
D40: TOTAL | E40: =E38+E28+E19 -> 345247320 | F40: =Table4[[#This Row],[Montant (Ar)]]/29 -> 11905080

Sheet Compte de résultat
A1: Charges | B1: Ventes | C1: Valeur Stock | D1: Stock (Kg) | E1: Marges
A2: =COGS!F38 -> 2.6944674e+08 | B2: ='Vente 2023-2024'!E19 -> 197454000 | C2: =D2*2000 -> 251140000 | D2: 125570
A3: ='Produits NPKSemences'!D10 -> 139039000 | B3: ='Vente 2023-2024'!E28 -> 99512400 | C3: =(Table6[[#This Row],[Ventes]]+B4)-Table6[[#This Row],[Charges]] -> 8754320 | D3: Benefices NPK
B4: ='Vente 2023-2024'!E38 -> 48280920
B5: ='Vente 2023-2024'!J7 -> 74907000 | C5: Vente non encaissée
A7: Total charges | B7: Total ventes encaissées | C7: Bénéfices nets 2025 | D7: Bénéfice brut après liquidation
A8: =SUM(A2) -> 2.6944674e+08 | B8: =SUM(B2) -> 197454000 | C8: =B8-A8 -> -71992744 | D8: =C8+C2+B5 -> 2.5405426e+08
G10: ROI/29mois
G11: Benef/mois
B15: =A2+A3 -> 4.0848574e+08 | C15: =SUM(B2:B5) -> 420154320 | D15: =(C15-B15)+C2 -> 2.6280858e+08 | E15: =D15/29 -> 9062364.7 | F15: =E15/4500 -> 2013.8588
B16: Total charges | C16: Total ventes | D16: RN+Stock | E16: RN/Mois Ar | F16: RN/Mois $
